{
    "Bio": "A Hindu man and a Muslim woman fall in love in a small village and move to Mumbai, where they have two children. However, growing religious tensions and erupting riots threaten to tear the family apart.",
    "Cast_List": [
        {
            "IMDB_ID": "nm0841552",
            "Name": "Arvind Swamy"
        },
        {
            "IMDB_ID": "nm0463539",
            "Name": "Manisha Koirala"
        },
        {
            "IMDB_ID": "nm0621937",
            "Name": "Nassar"
        },
        {
            "IMDB_ID": "nm1390149",
            "Name": "Kitty"
        },
        {
            "IMDB_ID": "nm1218624",
            "Name": "Master Harsha"
        },
        {
            "IMDB_ID": "nm1389854",
            "Name": "Master Hriday"
        },
        {
            "IMDB_ID": "nm0025627",
            "Name": "Tinnu Anand"
        },
        {
            "IMDB_ID": "nm0452021",
            "Name": "Akash Khurana"
        },
        {
            "IMDB_ID": "nm1377248",
            "Name": "Nagendra Prasad"
        },
        {
            "IMDB_ID": "nm0695177",
            "Name": "Prakash Raj"
        },
        {
            "IMDB_ID": "nm0007114",
            "Name": "Sonali Bendre"
        },
        {
            "IMDB_ID": "nm1115041",
            "Name": "M.V. Vasudeva Rao"
        },
        {
            "IMDB_ID": "nm1391274",
            "Name": "Ratnakar"
        },
        {
            "IMDB_ID": "nm0707723",
            "Name": "Rallapalli"
        },
        {
            "IMDB_ID": "nm1390550",
            "Name": "Deesh Mariwala"
        },
        {
            "IMDB_ID": "nm1390512",
            "Name": "Vinay Malhotra"
        },
        {
            "IMDB_ID": "nm1390666",
            "Name": "Pramod Menon"
        },
        {
            "IMDB_ID": "nm0038019",
            "Name": "Arun"
        },
        {
            "IMDB_ID": "nm1388212",
            "Name": "A.R.S."
        },
        {
            "IMDB_ID": "nm1388786",
            "Name": "Vijaya Chandrika"
        },
        {
            "IMDB_ID": "nm0705553",
            "Name": "Radhabai"
        },
        {
            "IMDB_ID": "nm0790660",
            "Name": "Sheela"
        },
        {
            "IMDB_ID": "nm1394724",
            "Name": "Minu Rathod"
        },
        {
            "IMDB_ID": "nm1394471",
            "Name": "Padmini Natarajan"
        },
        {
            "IMDB_ID": "nm1396015",
            "Name": "Sreesha"
        },
        {
            "IMDB_ID": "nm1391203",
            "Name": "Priya"
        },
        {
            "IMDB_ID": "nm2762787",
            "Name": "Chetana Das"
        }
    ],
    "Country": "India",
    "Directors": [
        "Mani Ratnam"
    ],
    "Genre": [
        "Drama",
        "Musical",
        "Romance"
    ],
    "Languages": [
        "Tamil",
        "Hindi"
    ],
    "Name": "Bombay",
    "Runtime": 141
}